LICENSE
README.md
setup.py
alephvault/http_storage/__init__.py
alephvault/http_storage/flask_app.py
alephvault/http_storage/core/__init__.py
alephvault/http_storage/core/converters.py
alephvault/http_storage/core/formats.py
alephvault/http_storage/core/json.py
alephvault/http_storage/core/responses.py
alephvault/http_storage/core/validation.py
alephvault/http_storage/engine/__init__.py
alephvault/http_storage/engine/path.py
alephvault/http_storage/engine/schemas.py
alephvault/http_storage/types/__init__.py
alephvault/http_storage/types/cursor.py
alephvault/http_storage/types/method_handlers.py
alephvault_http_mongodb_storage.egg-info/PKG-INFO
alephvault_http_mongodb_storage.egg-info/SOURCES.txt
alephvault_http_mongodb_storage.egg-info/dependency_links.txt
alephvault_http_mongodb_storage.egg-info/requires.txt
alephvault_http_mongodb_storage.egg-info/top_level.txt
sample/__init__.py
sample/universe_and_accounts.py