Metadata-Version: 2.1
Name: alephvault-http-mongodb-storage
Version: 0.0.8
Summary: A lightweight server to work as a simple storage for games, done with MongoDB and Flask
Home-page: https://github.com/AlephVault/http-mongodb-storage
Author: luismasuelli
Author-email: luismasuelli@hotmail.com
License: MIT
License-File: LICENSE
